Metadata-Version: 2.1
Name: Det_Calc
Version: 0.1
Summary: Detective Calculator
Author: Detective Thaghra
Classifier: Programming Language :: Python :: 3
Classifier: Operating System :: OS Independent
Classifier: License :: OSI Approved :: MIT License
License-File: LICENSE.txt
